AUTHORS
LICENSE
MANIFEST.in
README.md
setup.py
django_front_edit.egg-info/PKG-INFO
django_front_edit.egg-info/SOURCES.txt
django_front_edit.egg-info/dependency_links.txt
django_front_edit.egg-info/requires.txt
django_front_edit.egg-info/top_level.txt
front_edit/__init__.py
front_edit/apps.py
front_edit/compat.py
front_edit/conf.py
front_edit/context_processors.py
front_edit/forms.py
front_edit/settings.py
front_edit/urls.py
front_edit/utils.py
front_edit/views.py
front_edit/static/front_edit/css/editable.css
front_edit/static/front_edit/images/loading.gif
front_edit/static/front_edit/js/editable.js
front_edit/static/front_edit/js/jquery.min.js
front_edit/static/front_edit/js/jquery.tools.min.js
front_edit/templates/front_edit/loader.html
front_edit/templates/front_edit/includes/editable.html
front_edit/templates/front_edit/includes/form.html
front_edit/templates/front_edit/includes/form_fields.html
front_edit/templates/front_edit/includes/toolbar.html
front_edit/templatetags/__init__.py
front_edit/templatetags/front_edit_tags/__init__.py
front_edit/templatetags/front_edit_tags/arguments.py
front_edit/templatetags/front_edit_tags/tags.py