Metadata-Version: 1.1
Name: django-front-edit
Version: 1.2.1
Summary: Front end editing for Django.
Home-page: https://bitbucket.org/dwaiter/django-front-edit
Author: Dwaiter.com
Author-email: dev@dwaiter.com
License: BSD
Keywords: django front-end editing admin tools dynamic management utilities
Platform: UNKNOWN
Classifier: Development Status :: 5 - Production/Stable
Classifier: Environment :: Web Environment
Classifier: Intended Audience :: Developers
Classifier: License :: OSI Approved :: BSD License
Classifier: Natural Language :: English
Classifier: Operating System :: OS Independent
Classifier: Programming Language :: Python
Classifier: Programming Language :: Python :: 2
Classifier: Programming Language :: Python :: 2.7
Classifier: Programming Language :: Python :: 3
Classifier: Programming Language :: Python :: 3.2
Classifier: Programming Language :: Python :: 3.3
Classifier: Programming Language :: Python :: 3.4
Classifier: Topic :: Internet :: WWW/HTTP :: Dynamic Content
Classifier: Topic :: Internet :: WWW/HTTP :: Site Management
Classifier: Topic :: Software Development :: User Interfaces
Classifier: Topic :: Utilities
Classifier: Framework :: Django
